setup.cfg
setup.py
oprex/__init__.py
oprex/oprex.py
oprex/parsetab.py
oprex/tests.py
oprex.egg-info/PKG-INFO
oprex.egg-info/SOURCES.txt
oprex.egg-info/dependency_links.txt
oprex.egg-info/requires.txt
oprex.egg-info/top_level.txt