Metadata-Version: 1.0
Name: oprex
Version: 0.9.1
Summary: another python parser
Home-page: https://pypi.python.org/pypi/oprex/
Author: Ron Panduwana
Author-email: panduwana@gmail.com
License: UNKNOWN
Keywords: testing,logging,example
Platform: UNKNOWN
